<?xml version="1.0" encoding="UTF-8"?>
<Example Revision="10.60.0776" Name="Mmod" xmlns:xsi="http://www.w3.org/2001/XMLSchema-instance" xsi:noNamespaceSchemaLocation="../../.schema/example_restriction.xsd">
 <Categories>
  <Category Name="Overview">
   <Category Priority="270" Name="General"/>
  </Category>
  <Category Name="Industries">
   <Category Name="Machining"/>
  </Category>
  <Category Name="Applications">
   <Category Name="Finding/Locating"/>
  </Category>
  <Category Name="Modules">
   <Category Name="Buffer"/>
   <Category Name="Display"/>
   <Category Name="Graphics"/>
   <Category Name="Geometric Model Finder"/>
  </Category>
  <Category Name="What's New">
   <Category Name="Older"/>
   <Category Name="MIL 10.0 U44"/>       
  </Category>
 </Categories>
 <Description>This example demonstrates the usage of the Geometric Model Finder module. 
   </Description>
 <Languages>
  <Language>C#</Language>
  <Language>C++</Language>
  <Language>MIL CoPilot</Language>
  <LinuxLanguage>C++</LinuxLanguage>
  <LinuxLanguage>C#</LinuxLanguage>
 </Languages>
 <Functions>
  <Function>MappAlloc</Function>
  <Function>MappFree</Function>
  <Function>MappTimer</Function>
  <Function>MbufFree</Function>
  <Function>MbufLoad</Function>
  <Function>MbufRestore</Function>
  <Function>MdispAlloc</Function>
  <Function>MdispControl</Function>
  <Function>MdispFree</Function>
  <Function>MdispSelect</Function>
  <Function>MgraAllocList</Function>
  <Function>MgraClear</Function>
  <Function>MgraColor</Function>
  <Function>MgraFree</Function>
  <Function>MmodAlloc</Function>
  <Function>MmodAllocResult</Function>
  <Function>MmodControl</Function>
  <Function>MmodDefine</Function>
  <Function>MmodDraw</Function>
  <Function>MmodFind</Function>
  <Function>MmodFree</Function>
  <Function>MmodGetResult</Function>
  <Function>MmodPreprocess</Function>
  <Function>MsysAlloc</Function>
  <Function>MsysFree</Function>
 </Functions>
  <Notes>
  </Notes>
  <Licenses>
  <License>Geometric Model Finder</License>
 </Licenses>
 <Keywords>
  <Keyword>Object matching</Keyword>
  <Keyword>Geometric pattern matching</Keyword>
  <Keyword>Pattern recognition</Keyword>
  <Keyword>Feature matching</Keyword>
 </Keywords>
</Example>
