<?xml version="1.0" encoding="UTF-8"?>
<Example Revision="10.60.0776" Name="MultipleDatamatrixCodeRead" xmlns:xsi="http://www.w3.org/2001/XMLSchema-instance" xsi:noNamespaceSchemaLocation="../../.schema/example_restriction.xsd">

   <Categories>

        <Category Name="Overview">
            <Category Name="Advanced">
               <Category Name="Processing"/>
            </Category>
        </Category>

        <Category Name="Industries">
            <Category Name="Electronics"/>
            <Category Name="Packaging"/>
        </Category>

        <Category Name="Applications">
            <Category Name="Identifying"/>
            <Category Name="Finding/Locating"/>
        </Category>

      <Category Name="Modules">
         <Category Name="Code Reader"/>
         <Category Name="Blob Analysis"/>
         <Category Name="Buffer"/>
         <Category Name="Display"/>
         <Category Name="Graphics"/>
         <Category Name="Image Processing"/>
      </Category>

        <Category Name="What's New">
           <Category Name="MIL 10.0 PP1" New="1"/>
        </Category>

   </Categories>

    <Description>This example shows three techniques to locate and read multiple datamatrix codes
                        in an image. The first performs a single reading in the whole image.
                        The second performs multiple sequential readings in regions of interest (ROIs).
                        The third performs multiple parallel readings in ROIs.
    </Description>

    <Languages>
        <Language>C++</Language>
        <LinuxLanguage>C++</LinuxLanguage>
    </Languages>

   <Functions>
      <Function>MappAlloc</Function>
      <Function>MappControlMp</Function>
      <Function>MappFree</Function>
      <Function>MappInquireMp</Function>
      <Function>MappTimer</Function>
      <Function>MblobAlloc</Function>
      <Function>MblobAllocResult</Function>
      <Function>MblobCalculate</Function>
      <Function>MblobControl</Function>
      <Function>MblobFree</Function>
      <Function>MblobGetResult</Function>
      <Function>MblobSelect</Function>
      <Function>MbufAlloc2d</Function>
      <Function>MbufClear</Function>
      <Function>MbufCopy</Function>
      <Function>MbufFree</Function>
      <Function>MbufInquire</Function>
      <Function>MbufRestore</Function>
      <Function>MbufSetRegion</Function>
      <Function>McodeAlloc</Function>
      <Function>McodeAllocResult</Function>
      <Function>McodeControl</Function>
      <Function>McodeDraw</Function>
      <Function>McodeFree</Function>
      <Function>McodeGetResult</Function>
      <Function>McodeGetResultSingle</Function>
      <Function>McodeModel</Function>
      <Function>McodeRead</Function>
      <Function>McodeStream</Function>
      <Function>MdispAlloc</Function>
      <Function>MdispControl</Function>
      <Function>MdispFree</Function>
      <Function>MdispInquire</Function>
      <Function>MdispSelect</Function>
      <Function>MgraAllocList</Function>
      <Function>MgraClear</Function>
      <Function>MgraColor</Function>
      <Function>MgraFree</Function>
      <Function>MgraRectAngle</Function>
      <Function>MgraText</Function>
      <Function>MimBinarize</Function>
      <Function>MimDilate</Function>
      <Function>MimMorphic</Function>
      <Function>MimResize</Function>
      <Function>MsysAlloc</Function>
      <Function>MsysFree</Function>
      <Function>MthrAlloc</Function>
      <Function>MthrControl</Function>
      <Function>MthrFree</Function>
      <Function>MthrWait</Function>
      <Function>MthrWaitMultiple</Function>
   </Functions>
   <Licenses>
      <License>Image Analysis</License>
      <License>Identification</License>
   </Licenses>

    <Keywords>
        <Keyword>Matrix barcodes</Keyword>
        <Keyword>Region of interest</Keyword>
        <Keyword>ROI</Keyword>
        <Keyword>Morphology</Keyword>
        <Keyword>Graphical annotations</Keyword>
        <Keyword>Blob analysis</Keyword>
        <Keyword>Multithreading</Keyword>
    </Keywords>

</Example>
